{
    "registrar": {
        "_id": "6653c30921adb890f4515051",
        "name": "WEDOS",
        "domain": "wedos.com",
        "supportedRecordTypes": [
            "A",
            "AAAA",
            "NS",
            "CNAME",
            "MX",
            "SPF",
            "SRV",
            "CAA",
            "TXT",
            "TLSA",
            "SSHFP",
            "DKIM",
            "DMARC"
        ],
        "extraPaidRecordTypes": [],
        "ipv4": [],
        "ipv6": [],
        "nsServer": [
            "ns.wedos.net",
            "ns.wedos.eu",
            "ns.wedos.cz",
            "ns.wedos.com"
        ],
        "source": [
            {
                "method": "Documentation",
                "link": "https://kb.wedos.com/en/domain/dns-servers-of-wedos/",
                "notes": "ns.wedos.net, ns.wedos.eu, ns.wedos.cz, ns.wedos.com",
                "time": "2024-04-13T17:57:25+02:00"
            },
            {
                "method": "Documentation",
                "link": "https://www.wedos.com/domains/dns-management/",
                "notes": "Supported Records: A, AAAA, NS, CNAME, MX, SPF, SRV, CAA, TXT, TLSA, SSHFP and partial dnssec support",
                "time": "2024-03-15T20:37:00+01:00"
            },
            {
                "method": "Documentation",
                "link": "https://kb.wedos.com/en/e-mails/emails-spf-dkim-and-dmarc/",
                "notes": "DKIM and DMARC by them???",
                "time": "2024-04-13T18:06:02+02:00"
            }
        ]
    },
    "records": {
        "A": 339,
        "AAAA": 101,
        "NS": 344,
        "CNAME": 0,
        "MX": 0,
        "SPF": 0,
        "SRV": 0,
        "CAA": 15,
        "TXT": 0,
        "TLSA": 0,
        "SSHFP": 0,
        "DKIM": 0,
        "DMARC": 46
    },
    "unofficialRecords": {
        "DNSKEY": 35,
        "DS": 29
    },
    "domains": 344,
    "percent": 0.00034400309602786427
}